image_builder_library/__init__.py
image_builder_library/cli.py
image_builder_library/image_builder_library.py
image_builder_library-0.1.0.dist-info/AUTHORS.rst
image_builder_library-0.1.0.dist-info/METADATA
image_builder_library-0.1.0.dist-info/WHEEL
image_builder_library-0.1.0.dist-info/entry_points.txt
image_builder_library-0.1.0.dist-info/top_level.txt
image_builder_library-0.1.0.dist-info/RECORD
